voice_mode/__init__.py
voice_mode/__main__.py
voice_mode/__version__.py
voice_mode/cli.py
voice_mode/config.py
voice_mode/conversation_logger.py
voice_mode/core.py
voice_mode/dependencies.yaml
voice_mode/openai_error_parser.py
voice_mode/pronounce.py
voice_mode/provider_discovery.py
voice_mode/providers.py
voice_mode/server.py
voice_mode/shared.py
voice_mode/simple_failover.py
voice_mode/statistics.py
voice_mode/statistics_tracking.py
voice_mode/streaming.py
voice_mode/version.py
voice_mode/whisper_model_unified.py
voice_mode/cli_commands/__init__.py
voice_mode/cli_commands/claude.py
voice_mode/cli_commands/exchanges.py
voice_mode/cli_commands/hook.py
voice_mode/cli_commands/pronounce_commands.py
voice_mode/cli_commands/transcribe.py
voice_mode/data/default_pronunciation.yaml
voice_mode/data/versions.json
voice_mode/exchanges/__init__.py
voice_mode/exchanges/conversations.py
voice_mode/exchanges/filters.py
voice_mode/exchanges/formatters.py
voice_mode/exchanges/models.py
voice_mode/exchanges/reader.py
voice_mode/exchanges/stats.py
voice_mode/frontend/README.md
voice_mode/frontend/next-env.d.ts
voice_mode/frontend/next.config.mjs
voice_mode/frontend/package-lock.json
voice_mode/frontend/package.json
voice_mode/frontend/pnpm-lock.yaml
voice_mode/frontend/postcss.config.mjs
voice_mode/frontend/tailwind.config.ts
voice_mode/frontend/tsconfig.json
voice_mode/frontend/.next/BUILD_ID
voice_mode/frontend/.next/app-build-manifest.json
voice_mode/frontend/.next/app-path-routes-manifest.json
voice_mode/frontend/.next/build-manifest.json
voice_mode/frontend/.next/export-marker.json
voice_mode/frontend/.next/images-manifest.json
voice_mode/frontend/.next/next-minimal-server.js.nft.json
voice_mode/frontend/.next/next-server.js.nft.json
voice_mode/frontend/.next/package.json
voice_mode/frontend/.next/prerender-manifest.json
voice_mode/frontend/.next/react-loadable-manifest.json
voice_mode/frontend/.next/required-server-files.json
voice_mode/frontend/.next/routes-manifest.json
voice_mode_enhanced-6.0.2.post1.dist-info/METADATA
voice_mode_enhanced-6.0.2.post1.dist-info/WHEEL
voice_mode_enhanced-6.0.2.post1.dist-info/entry_points.txt
voice_mode_enhanced-6.0.2.post1.dist-info/licenses/LICENSE
voice_mode_enhanced-6.0.2.post1.dist-info/RECORD
